LICENSE
README.md
setup.cfg
setup.py
directory2docker/__init__.py
directory2docker/app.py
directory2docker.egg-info/PKG-INFO
directory2docker.egg-info/SOURCES.txt
directory2docker.egg-info/dependency_links.txt
directory2docker.egg-info/not-zip-safe
directory2docker.egg-info/top_level.txt