Metadata-Version: 2.1
Name: directory2docker
Version: 0.0.6
Summary: Python Package Boilerplate
Author: Sachin Chandra
Author-email: sachin@netbook.ai
License: MIT License
Keywords: Package python enviroment as docker
Classifier: Programming Language :: Python
Classifier: Programming Language :: Python :: 3
Classifier: Operating System :: OS Independent
License-File: LICENSE
